pymirror/__init__.py
pymirror/__version__.py
pymirror/api_upload.py
pymirror/cli.py
pymirror/config.py
pymirror/data/more_links.json
pymirror/data/servers_data.json
pymirror/experimental/__init__.py
pymirror/experimental/more_links.py
pymirror/handlers.py
pymirror/helpers.py
pymirror/main.py
pymirror/mirroredto.py
pymirror/multiup.py
pymirror/run.py
pymirror/start_driver.py
pymirror/tests/__init__.py
pymirror/tests/test_pymirror.py
pymirror-0.4.3.dist-info/entry_points.txt
pymirror-0.4.3.dist-info/LICENSE
pymirror-0.4.3.dist-info/WHEEL
pymirror-0.4.3.dist-info/METADATA
pymirror-0.4.3.dist-info/RECORD
