Metadata-Version: 2.1
Name: pymirror
Version: 0.4.3
Summary: Upload files to Multiple Mirror
License: MIT
Author: Mohammad Alyetama
Author-email: malyetama@pm.me
Requires-Python: >=3.7,<4.0
Classifier: License :: OSI Approved :: MIT License
Classifier: Programming Language :: Python :: 3
Classifier: Programming Language :: Python :: 3.10
Classifier: Programming Language :: Python :: 3.7
Classifier: Programming Language :: Python :: 3.8
Classifier: Programming Language :: Python :: 3.9
Requires-Dist: dracula (>=0.1.3)
Requires-Dist: loguru (>=0.5.3)
Requires-Dist: psutil (>=5.8.0)
Requires-Dist: requests (>=2.28.0)
Requires-Dist: rich (>=10.13.0)
Requires-Dist: selenium (>=4.1.0)
Requires-Dist: speedtest (>=0.0.1,<0.0.2)
Requires-Dist: webdriver-manager (>=3.5.2)
